statsdecor/__init__.py
statsdecor/clients.py
statsdecor/context.py
statsdecor/decorators.py
statsdecor-0.4.2.dist-info/LICENSE
statsdecor-0.4.2.dist-info/METADATA
statsdecor-0.4.2.dist-info/WHEEL
statsdecor-0.4.2.dist-info/top_level.txt
statsdecor-0.4.2.dist-info/RECORD
