Metadata-Version: 2.1
Name: statsdecor
Version: 0.4.2
Summary: A set of decorators and helper methods for adding statsd metrics to applications.
Home-page: https://github.com/amcintosh/statsdecor
Author: Freshbooks Dev Team
Author-email: opensource@freshbooks.com
Maintainer: Andrew McIntosh
Maintainer-email: andrew@amcintosh.net
License: MIT
Keywords: statsd,stats
Classifier: Development Status :: 4 - Beta
Classifier: Intended Audience :: Developers
Classifier: License :: OSI Approved :: MIT License
Classifier: Natural Language :: English
Classifier: Programming Language :: Python
Classifier: Programming Language :: Python :: 3
Classifier: Programming Language :: Python :: 3 :: Only
Classifier: Programming Language :: Python :: 3.8
Classifier: Programming Language :: Python :: 3.9
Classifier: Programming Language :: Python :: 3.10
Classifier: Programming Language :: Python :: 3.11
Classifier: Programming Language :: Python :: 3.12
Classifier: Programming Language :: Python :: 3.13
License-File: LICENSE
Requires-Dist: statsd
Requires-Dist: datadog
